{
  "contenidos": [
    {
      "dia": "1",
      "titulo": "recetas saludables finales",
      "descripcion": "Praesent sapien massa, convallis a pellentesque nec",
      "media": "youtube.com",
      "id": 1
    },
    {
      "id": 2,
      "titulo": "Karen",
      "descripcion": "Praesent sapien massa, convallis a pellentesque nec",
      "media": "youtube.com",
      "dia": 1
    },
    {
      "id": 3,
      "titulo": "Josue",
      "descripcion": "Praesent sapien massa, convallis a pellentesque nec",
      "media": "youtube.com",
      "dia": 2
    },
    {
      "dia": "2",
      "titulo": "Cardio para perder grasa",
      "descripcion": "Aprende cardio para perder grasa",
      "media": "youtube.com",
      "id": 6
    },
    {
      "dia": "2",
      "titulo": "Yoga para tu vida",
      "descripcion": "Mejores tips para integrar el Yoga en tu diario vivir.",
      "media": "youtube.com/yoga",
      "id": 7
    }
  ],
  "usuarios": [
    {
      "id": 1,
      "rol": "admin",
      "usuario": "root",
      "contraseña": "123456"
    },
    {
      "id": 2,
      "rol": "ventas",
      "usuario": "ventas",
      "contraseña": "123456"
    },
    {
      "id": 3,
      "rol": "global",
      "usuario": "global",
      "contraseña": "123456"
    }
  ]
}